openfeature/contrib/hook/opentelemetry/__init__.py
openfeature_hooks_opentelemetry-0.3.0.dist-info/licenses/LICENSE
openfeature_hooks_opentelemetry-0.3.0.dist-info/WHEEL
openfeature_hooks_opentelemetry-0.3.0.dist-info/entry_points.txt
openfeature_hooks_opentelemetry-0.3.0.dist-info/METADATA
openfeature_hooks_opentelemetry-0.3.0.dist-info/RECORD
