Metadata-Version: 2.4
Name: openfeature-hooks-opentelemetry
Version: 0.3.0
Summary: OpenTelemetry hooks for the OpenFeature Python SDK
Keywords: 
Author: OpenFeature
Author-email: OpenFeature <openfeature-core@groups.io>
License-Expression: Apache-2.0
License-File: LICENSE
Classifier: Programming Language :: Python
Classifier: Programming Language :: Python :: 3
Requires-Dist: openfeature-sdk>=0.8.4
Requires-Dist: opentelemetry-api
Requires-Dist: opentelemetry-semantic-conventions>=0.50b0
Requires-Python: >=3.9
Project-URL: Homepage, https://github.com/open-feature/python-sdk-contrib
